key_vault_interface/__init__.py
key_vault_interface/exceptions.py
key_vault_interface/key_vault_interface.py
tests/__init__.py
tests/test_key_vault_interface.py
key_vault_interface-1.0.8.dist-info/LICENSE
key_vault_interface-1.0.8.dist-info/METADATA
key_vault_interface-1.0.8.dist-info/WHEEL
key_vault_interface-1.0.8.dist-info/top_level.txt
key_vault_interface-1.0.8.dist-info/RECORD
