Metadata-Version: 2.2
Name: key-vault-interface
Version: 1.0.8
Summary: A simple package to work as an interface with a key; at the moment only supporting Azure.
Author-email: Mirco Domenicale <m.domenicale@40-factory.com>
Classifier: Programming Language :: Python :: 3
Classifier: License :: OSI Approved :: MIT License
Requires-Python: >=3.8
License-File: LICENSE
Requires-Dist: azure-identity>=1.19.0
Requires-Dist: azure-keyvault-secrets>=4.9.0
Requires-Dist: yarg>=0.1.9
Provides-Extra: dev
Requires-Dist: pytest>=8.3.4; extra == "dev"
Requires-Dist: pipdeptree>=2.24.0; extra == "dev"
Requires-Dist: pytest-mock==3.14.0; extra == "dev"
Requires-Dist: python-dotenv==1.0.1; extra == "dev"
Requires-Dist: wheel==0.45.1; extra == "dev"
Requires-Dist: twine==6.0.1; extra == "dev"
Requires-Dist: build==1.2.2.post1; extra == "dev"
Provides-Extra: docs
Requires-Dist: sphinx>=8.1.3; extra == "docs"
Requires-Dist: docopt>=0.6.2; extra == "docs"
Requires-Dist: ipython>=8.12.3; extra == "docs"
Requires-Dist: nbconvert>=7.16.4; extra == "docs"
Requires-Dist: pdoc==15.0.1; extra == "docs"
Requires-Dist: sphinx-markdown-builder==0.6.7; extra == "docs"
